aac_processors/__init__.py
aac_processors/apple_panels_processor.py
aac_processors/base_processor.py
aac_processors/cli.py
aac_processors/coughdrop_processor.py
aac_processors/dot_processor.py
aac_processors/file_processor.py
aac_processors/gridset_processor.py
aac_processors/opml_processor.py
aac_processors/snap_processor.py
aac_processors/sqlite_processor.py
aac_processors/touchchat_processor.py
aac_processors/tree_structure.py
aac_processors/viewer.py
aac_processors/optional/screenshot_processor.py
aac_processors-0.1.8.dist-info/METADATA
aac_processors-0.1.8.dist-info/WHEEL
aac_processors-0.1.8.dist-info/entry_points.txt
aac_processors-0.1.8.dist-info/licenses/LICENSE
aac_processors-0.1.8.dist-info/RECORD
