Metadata-Version: 2.4
Name: aac-processors
Version: 0.1.8
Summary: Process and convert between different AAC file formats
Project-URL: Homepage, https://github.com/willwade/AACProcessors
Project-URL: Repository, https://github.com/willwade/AACProcessors.git
Author-email: Will Wade <willwade@gmail.com>
License: AGPL-3.0-or-later
License-File: LICENSE
Classifier: Development Status :: 3 - Alpha
Classifier: Intended Audience :: Developers
Classifier: License :: OSI Approved :: GNU Affero General Public License v3 or later (AGPLv3+)
Classifier: Programming Language :: Python :: 3
Classifier: Programming Language :: Python :: 3.9
Classifier: Programming Language :: Python :: 3.10
Classifier: Programming Language :: Python :: 3.11
Requires-Python: >=3.9
Requires-Dist: beautifulsoup4>=4.12.2
Requires-Dist: lxml>=4.9.3
Requires-Dist: openpyxl>=3.1.2
Requires-Dist: pandas>=2.1.1
Provides-Extra: dev
Requires-Dist: black>=23.9.1; extra == 'dev'
Requires-Dist: cssselect; extra == 'dev'
Requires-Dist: mypy>=1.5.1; extra == 'dev'
Requires-Dist: pandas-stubs; extra == 'dev'
Requires-Dist: pytest-cov>=4.1.0; extra == 'dev'
Requires-Dist: pytest>=7.4.2; extra == 'dev'
Requires-Dist: ruff>=0.0.291; extra == 'dev'
Requires-Dist: types-beautifulsoup4; extra == 'dev'
Requires-Dist: types-html5lib; extra == 'dev'
Requires-Dist: types-lxml; extra == 'dev'
Requires-Dist: types-openpyxl; extra == 'dev'
Provides-Extra: screenshot
Requires-Dist: easyocr>=1.7.1; extra == 'screenshot'
Requires-Dist: numpy>=1.24.0; extra == 'screenshot'
Requires-Dist: opencv-python>=4.8.0; extra == 'screenshot'
Requires-Dist: pillow>=10.0.0; extra == 'screenshot'
Requires-Dist: pytesseract>=0.3.10; extra == 'screenshot'
